{
  "project_info": {
    "project_number": "120744957160",
    "project_id": "mayoraaa-4a1c1",
    "storage_bucket": "mayoraaa-4a1c1.appspot.com"
  },
  "client": [
    {
      "client_info": {
        "mobilesdk_app_id": "1:120744957160:android:7e7ceac90422460b54255d",
        "android_client_info": {
          "package_name": "com.mayora.untitled2"
        }
      },
      "oauth_client": [
        {
          "client_id": "120744957160-99dc2hvu1st809et7pbh7one1rn59rn5.apps.googleusercontent.com",
          "client_type": 3
        }
      ],
      "api_key": [
        {
          "current_key": "AIzaSyD1hkrt-Y8fU_pOnv-96ghMdqTseBybz5o"
        }
      ],
      "services": {
        "appinvite_service": {
          "other_platform_oauth_client": [
            {
              "client_id": "120744957160-99dc2hvu1st809et7pbh7one1rn59rn5.apps.googleusercontent.com",
              "client_type": 3
            }
          ]
        }
      }
    }
  ],
  "configuration_version": "1"
}